scpmanWechat/__init__.py
scpmanWechat-1.0.3.dist-info/LICENSE
scpmanWechat-1.0.3.dist-info/METADATA
scpmanWechat-1.0.3.dist-info/WHEEL
scpmanWechat-1.0.3.dist-info/top_level.txt
scpmanWechat-1.0.3.dist-info/RECORD
