Metadata-Version: 2.1
Name: scpmanWechat
Version: 1.0.3
Summary: Send Message to Wechat Application
Home-page: https://github.com/freeddser/scpmanWechat
Author: scpman
Author-email: scpman@live.com
Maintainer: scpman
Maintainer-email: scpman@live.com
License: UNKNOWN
Platform: UNKNOWN
Classifier: Programming Language :: Python :: 3
Classifier: License :: OSI Approved :: MIT License
Classifier: Operating System :: OS Independent
Requires-Python: >=3.0
